main.py
universal_json_converter-1.0.0.dist-info/licenses/LICENSE
universal_json_converter-1.0.0.dist-info/METADATA
universal_json_converter-1.0.0.dist-info/WHEEL
universal_json_converter-1.0.0.dist-info/entry_points.txt
universal_json_converter-1.0.0.dist-info/top_level.txt
universal_json_converter-1.0.0.dist-info/RECORD
