Metadata-Version: 2.4
Name: universal-json-converter
Version: 1.0.0
Summary: A CLI tool to convert files to/from JSON efficiently with large file support
Home-page: https://github.com/Siddharth-lal-13/universal-json-converter
Author: Siddharth Lal
Author-email: siddharthlal99@gmail.com
Classifier: Programming Language :: Python :: 3
Classifier: License :: OSI Approved :: MIT License
Classifier: Operating System :: OS Independent
Requires-Python: >=3.7
License-File: LICENSE
Requires-Dist: pandas
Requires-Dist: pyyaml
Requires-Dist: openpyxl
Requires-Dist: pyarrow
Dynamic: author
Dynamic: author-email
Dynamic: classifier
Dynamic: description
Dynamic: description-content-type
Dynamic: home-page
Dynamic: license-file
Dynamic: requires-dist
Dynamic: requires-python
Dynamic: summary
